django_qiniu/__init__.py
django_qiniu/admin.py
django_qiniu/apps.py
django_qiniu/models.py
django_qiniu/serializers.py
django_qiniu/tests.py
django_qiniu/views.py
django_qiniu/management/__init__.py
django_qiniu/management/commands/__init__.py
django_qiniu/management/commands/update_resource.py
django_qiniu/migrations/0001_initial.py
django_qiniu/migrations/0002_bucket_https.py
django_qiniu/migrations/0003_token.py
django_qiniu/migrations/0004_livebucket.py
django_qiniu/migrations/0005_resource__duration.py
django_qiniu/migrations/__init__.py
django_qiniu_app-1.1.1.dist-info/LICENSE
django_qiniu_app-1.1.1.dist-info/METADATA
django_qiniu_app-1.1.1.dist-info/WHEEL
django_qiniu_app-1.1.1.dist-info/top_level.txt
django_qiniu_app-1.1.1.dist-info/RECORD
