Metadata-Version: 2.1
Name: django-qiniu-app
Version: 1.1.1
Summary: django的七牛app
Home-page: https://github.com/ramwin/django-qiniu-app
Author: Xiang Wang
Author-email: ramwin@qq.com
License: UNKNOWN
Platform: UNKNOWN
Classifier: Programming Language :: Python :: 2
Classifier: Programming Language :: Python :: 3
Classifier: License :: OSI Approved :: GNU Affero General Public License v3 or later (AGPLv3+)
Classifier: Operating System :: OS Independent
Requires-Dist: django
Requires-Dist: djangorestframework
Requires-Dist: qiniu
